<item>
<title>Star Trek: The Motion Picture (1979) [COLOR red] (HD) [/COLOR]</title>
<link>http://movreel.com/l5akorickh2k</link>
<thumbnail>http://www.coverwhiz.com/content/Star-Trek-The-Motion-Picture.jpg</thumbnail>
</item>

<item>
<title>Star Trek: The Wrath of Khan (1982) [COLOR red] (HD) [/COLOR]</title>
<link>http://movreel.com/cqydv698hlq8</link>
<thumbnail>http://redringsofredemption.files.wordpress.com/2014/01/star-trek-ii-the-wrath-of-khan-poster-star-trek-movies-8475612-1707-2560.jpg</thumbnail>
</item>

<item>
<title>Star Trek III: The Search for Spock (1984) [COLOR red] (HD) [/COLOR]</title>
<link>http://movreel.com/phqr10gvv0y1</link>
<thumbnail>http://1.bp.blogspot.com/-ftiuODRPgg8/UOsK12SVFWI/AAAAAAAAB4Q/QoZ0KYiMd4E/s1600/ST3.jpg</thumbnail>
</item>

<item>
<title>Star Trek IV: The Voyage Home (1986) [COLOR red] (HD) [/COLOR]</title>
<link>http://movreel.com/yw7fieoxf889</link>
<thumbnail>http://manilovefilms.com/wp-content/uploads/2013/05/st-voyagehome-poster.jpg</thumbnail>
</item>

<item>
<title>Star Trek V: The Final Frontier (1989) [COLOR red] (HD) [/COLOR]</title>
<link>http://movreel.com/lxfz3q6efdec</link>
<thumbnail>http://2.bp.blogspot.com/-lV3sQkCPajw/UA6MwB7r57I/AAAAAAAAJZE/4yVehnFHvs0/s1600/The+Final+Frontier+%281989%29+1.jpg</thumbnail>
</item>

<item>
<title>Star Trek VI: The Undiscovered Country (1991) [COLOR red] (HD) [/COLOR]</title>
<link>http://movreel.com/c80y9d5diff9</link>
<thumbnail>http://dvdbash.files.wordpress.com/2012/04/star_trek_06_the_undiscovered_country_1_dvdbash.jpg</thumbnail>
</item>

<item>
<title>Star Trek: Generations (1994) [COLOR red] (HD) [/COLOR]</title>
<link>http://movreel.com/c3mm2qwjw9ug</link>
<thumbnail>http://www.coverwhiz.com/content/Star-Trek-Generations.jpg</thumbnail>
</item>

<item>
<title>Star Trek: First Contact (1996) [COLOR red] (HD) [/COLOR]</title>
<link>http://movreel.com/hcv91aq5w9pb</link>
<thumbnail>http://www.blankmaninc.com/wp-content/uploads/2013/06/first-contact-poster.jpg</thumbnail>
</item>

<item>
<title>Star Trek: Insurrection (1998) [COLOR red] (HD) [/COLOR]</title>
<link>http://movreel.com/sks8ht1qbqk0</link>
<thumbnail>http://cdn3-www.craveonline.com/assets/uploads/2013/05/Insurrection-poster.jpg</thumbnail>
</item>

<item>
<title>Star Trek: Nemesis (2002) [COLOR red] (HD) [/COLOR]</title>
<link>http://movreel.com/53y6tnr0rbz7</link>
<thumbnail>http://upload.wikimedia.org/wikipedia/fi/3/36/Star_Trek_Nemesis.jpg</thumbnail>
</item>

<item>
<title>Star Trek (2009) [COLOR red] (HD) [/COLOR]</title>
<link>http://movreel.com/eipxjak0fctl</link>
<thumbnail>http://3219a2.medialib.glogster.com/jediking8403/media/a2/a2597a92c654f7ccf971162c25185f50083dad2d/star-trek-film-dvd-cover.jpg</thumbnail>
</item>

<item>
<title>Star Trek: Into Darkness (2013) [COLOR red] (HD) [/COLOR]</title>
<link>http://movreel.com/djho67hg8b34</link>
<thumbnail>http://www.impawards.com/2013/posters/star_trek_into_darkness_xlg.jpg</thumbnail>
</item>
